vision_tile_query/__init__.py
vision_tile_query/config.py
vision_tile_query/tile_creator.py
vision_tile_query/contrib/__init__.py
vision_tile_query/contrib/model_creator.py
vision_tile_query/utils/__init__.py
vision_tile_query/utils/database.py
vision_tile_query/utils/logger.py
vision_tile_query/utils/metadata.py
vision_tile_query-0.0.5.dist-info/DESCRIPTION.rst
vision_tile_query-0.0.5.dist-info/METADATA
vision_tile_query-0.0.5.dist-info/RECORD
vision_tile_query-0.0.5.dist-info/WHEEL
vision_tile_query-0.0.5.dist-info/metadata.json
vision_tile_query-0.0.5.dist-info/top_level.txt
