Metadata-Version: 2.0
Name: vision-tile-query
Version: 0.0.5
Summary: Library for creating MVT SQL query
Home-page: https://github.com/eos-vision/vision_tile_query
Author: Andrey Sorokin
Author-email: andreysrkn@eosda.com
License: Unlicense
Platform: UNKNOWN
Classifier: Development Status :: 4 - Beta
Classifier: Intended Audience :: Developers
Classifier: License :: Public Domain
Classifier: Operating System :: OS Independent
Classifier: Programming Language :: Python
Classifier: Programming Language :: Python :: 3
Classifier: Topic :: Database
Requires-Dist: SQLAlchemy
Requires-Dist: mercantile
Requires-Dist: geoalchemy2
